{
  "Object": {
    "Name": "Custom_Model",
    "Transform": {
      "posX": 34.139164,
      "posY": 1.452248,
      "posZ": -10.3144875,
      "rotX": 0.00113560306,
      "rotY": 135.005173,
      "rotZ": -0.001134517,
      "scaleX": 1,
      "scaleY": 1,
      "scaleZ": 1
    },
    "Nickname": "Cargo Pallet [Heavy Cover]",
    "Description": "Heavy Cover:\nAll except AT-ST, T-47\n\nCrates:\nTrooper - Difficult\nG. Vehicle - Open\nRepulsor - Open\n\nOnly Crates provide Cover, obscure LOS and hinder Movement, Pallets on the ground have no effect\n\nSpecial Thanks: www.imperialterrain.com",
    "GMNotes": "",
    "ColorDiffuse": {
      "r": 1,
      "g": 1,
      "b": 1
    },
    "Locked": true,
    "Grid": true,
    "Snap": true,
    "IgnoreFoW": false,
    "MeasureMovement": false,
    "DragSelectable": true,
    "Autoraise": true,
    "Sticky": true,
    "Tooltip": true,
    "GridProjection": false,
    "HideWhenFaceDown": false,
    "Hands": false,
    "CustomMesh": {
      "MeshURL": "http://cloud-3.steamusercontent.com/ugc/785234540542826602/B0476F42FA35B268E716748542F74AF7C2FC93FC/",
      "DiffuseURL": "http://cloud-3.steamusercontent.com/ugc/785234540542822457/CC3F0DC02DD35143BD5DAF27A694D9EC1BA6A98A/",
      "NormalURL": "",
      "ColliderURL": "http://cloud-3.steamusercontent.com/ugc/785234540542823541/5F7BBC41E9FB517BE41C845282B3A731EB050150/",
      "Convex": true,
      "MaterialIndex": 3,
      "TypeIndex": 0,
      "CastShadows": true
    },
    "LuaScript": "#include ./Cargo_Pallet_Heavy_Cover.c7bc46.lua",
    "LuaScriptState": "",
    "XmlUI": "",
    "GUID": "c7bc46"
  },
  "StatesPaths": {}
}
